[{"id":1,"name":"Karoly Fozzard","email":"kfozzard0@simplemachines.org"},
{"id":2,"name":"Marie Kingsnode","email":"mkingsnode1@i2i.jp"},
{"id":3,"name":"Garwood Rallin","email":"grallin2@google.com.hk"},
{"id":4,"name":"Tynan Fligg","email":"tfligg3@wikimedia.org"},
{"id":5,"name":"Augusto Warnes","email":"awarnes4@newyorker.com"},
{"id":6,"name":"Adan Mabbot","email":"amabbot5@accuweather.com"},
{"id":7,"name":"Netti Wragg","email":"nwragg6@bbb.org"},
{"id":8,"name":"Zacharie Wintour","email":"zwintour7@loc.gov"},
{"id":9,"name":"Hart Grzelewski","email":"hgrzelewski8@google.cn"},
{"id":10,"name":"Fitz Kennerley","email":"fkennerley9@salon.com"},
{"id":11,"name":"Caspar Woodeson","email":"cwoodesona@privacy.gov.au"},
{"id":12,"name":"Broddie Brackstone","email":"bbrackstoneb@ucla.edu"},
{"id":13,"name":"Lamar De Gogay","email":"ldec@51.la"},
{"id":14,"name":"Cass Ivchenko","email":"civchenkod@mlb.com"},
{"id":15,"name":"Vinny Bottom","email":"vbottome@usnews.com"},
{"id":16,"name":"Oriana Gahan","email":"ogahanf@etsy.com"},
{"id":17,"name":"Amelie Bewfield","email":"abewfieldg@independent.co.uk"},
{"id":18,"name":"Livvie Newns","email":"lnewnsh@seattletimes.com"},
{"id":19,"name":"Amitie Farnill","email":"afarnilli@friendfeed.com"},
{"id":20,"name":"Charlton Bladen","email":"cbladenj@free.fr"},
{"id":21,"name":"Ely Eat","email":"eeatk@geocities.jp"},
{"id":22,"name":"Jess Speirs","email":"jspeirsl@washington.edu"},
{"id":23,"name":"Shirleen Housby","email":"shousbym@123-reg.co.uk"},
{"id":24,"name":"Manuel Renison","email":"mrenisonn@shareasale.com"},
{"id":25,"name":"Anthea McKeran","email":"amckerano@ocn.ne.jp"},
{"id":26,"name":"Kristina Siemon","email":"ksiemonp@posterous.com"},
{"id":27,"name":"Emlyn Devaney","email":"edevaneyq@nih.gov"},
{"id":28,"name":"Cobbie Chessell","email":"cchessellr@usnews.com"},
{"id":29,"name":"Angelo Adolfsen","email":"aadolfsens@indiatimes.com"},
{"id":30,"name":"Rhea Bartlomieczak","email":"rbartlomieczakt@unc.edu"},
{"id":31,"name":"Wakefield Skirvane","email":"wskirvaneu@utexas.edu"},
{"id":32,"name":"Maire Pettegree","email":"mpettegreev@gravatar.com"},
{"id":33,"name":"Blane Tomczykiewicz","email":"btomczykiewiczw@ocn.ne.jp"},
{"id":34,"name":"Ingrim Grabham","email":"igrabhamx@prweb.com"},
{"id":35,"name":"Alonzo Lorenzetto","email":"alorenzettoy@indiegogo.com"},
{"id":36,"name":"Ronna Richold","email":"rricholdz@dailymail.co.uk"},
{"id":37,"name":"Moll Thorwarth","email":"mthorwarth10@dion.ne.jp"},
{"id":38,"name":"Collin Collison","email":"ccollison11@zimbio.com"},
{"id":39,"name":"Amara Lambshine","email":"alambshine12@ning.com"},
{"id":40,"name":"Ferdinanda Beck","email":"fbeck13@marketwatch.com"},
{"id":41,"name":"Gene Sex","email":"gsex14@wix.com"},
{"id":42,"name":"Tobey Andrasch","email":"tandrasch15@economist.com"},
{"id":43,"name":"Muffin Fitzsimon","email":"mfitzsimon16@state.gov"},
{"id":44,"name":"Carolynn Gave","email":"cgave17@blog.com"},
{"id":45,"name":"Christophorus Longcake","email":"clongcake18@creativecommons.org"},
{"id":46,"name":"Gherardo Iannelli","email":"giannelli19@cnet.com"},
{"id":47,"name":"Carleen Liddard","email":"cliddard1a@bing.com"},
{"id":48,"name":"Monique Rillett","email":"mrillett1b@tinyurl.com"},
{"id":49,"name":"Astra Frany","email":"afrany1c@wsj.com"},
{"id":50,"name":"Cesare Bruyntjes","email":"cbruyntjes1d@people.com.cn"},
{"id":51,"name":"Dwight Culbard","email":"dculbard1e@newyorker.com"},
{"id":52,"name":"Deny Mazdon","email":"dmazdon1f@squidoo.com"},
{"id":53,"name":"Adan Trenoweth","email":"atrenoweth1g@merriam-webster.com"},
{"id":54,"name":"Lovell Bashford","email":"lbashford1h@washington.edu"},
{"id":55,"name":"Winslow Satch","email":"wsatch1i@photobucket.com"},
{"id":56,"name":"Zachary Bampkin","email":"zbampkin1j@a8.net"},
{"id":57,"name":"Jessika Sansome","email":"jsansome1k@printfriendly.com"},
{"id":58,"name":"Lacey Althorp","email":"lalthorp1l@smugmug.com"},
{"id":59,"name":"Lindsey Ferrieroi","email":"lferrieroi1m@theguardian.com"},
{"id":60,"name":"Heall Matyushenko","email":"hmatyushenko1n@barnesandnoble.com"},
{"id":61,"name":"Rice Shillom","email":"rshillom1o@engadget.com"},
{"id":62,"name":"Rosanne Letten","email":"rletten1p@hao123.com"},
{"id":63,"name":"Lavinia Dearnley","email":"ldearnley1q@harvard.edu"},
{"id":64,"name":"Nariko Jaukovic","email":"njaukovic1r@tamu.edu"},
{"id":65,"name":"Giffy Lightning","email":"glightning1s@spotify.com"},
{"id":66,"name":"Trever Penrice","email":"tpenrice1t@economist.com"},
{"id":67,"name":"Horton Clackers","email":"hclackers1u@walmart.com"},
{"id":68,"name":"Chandal Pignon","email":"cpignon1v@cornell.edu"},
{"id":69,"name":"Goldarina Tytcomb","email":"gtytcomb1w@4shared.com"},
{"id":70,"name":"Burnaby Castelluzzi","email":"bcastelluzzi1x@ycombinator.com"},
{"id":71,"name":"Gale Edgeworth","email":"gedgeworth1y@blinklist.com"},
{"id":72,"name":"Legra Bradnum","email":"lbradnum1z@last.fm"},
{"id":73,"name":"Pasquale Sirrell","email":"psirrell20@goo.gl"},
{"id":74,"name":"Clemmie Scud","email":"cscud21@sfgate.com"},
{"id":75,"name":"Harlan Winslet","email":"hwinslet22@squarespace.com"},
{"id":76,"name":"Claudette Kernocke","email":"ckernocke23@sogou.com"},
{"id":77,"name":"Trumaine Gillingwater","email":"tgillingwater24@amazon.co.uk"},
{"id":78,"name":"Northrop Wassung","email":"nwassung25@ocn.ne.jp"},
{"id":79,"name":"Constancy Barlthrop","email":"cbarlthrop26@mac.com"},
{"id":80,"name":"Andree Bothe","email":"abothe27@uol.com.br"},
{"id":81,"name":"Doria Durkin","email":"ddurkin28@irs.gov"},
{"id":82,"name":"Bonnie Panchin","email":"bpanchin29@google.com.au"},
{"id":83,"name":"Nomi Theyer","email":"ntheyer2a@dmoz.org"},
{"id":84,"name":"Mireille Vasyutochkin","email":"mvasyutochkin2b@opensource.org"},
{"id":85,"name":"Elliot Buchett","email":"ebuchett2c@blog.com"},
{"id":86,"name":"Esther Schimek","email":"eschimek2d@diigo.com"},
{"id":87,"name":"Ralf Bisco","email":"rbisco2e@msn.com"},
{"id":88,"name":"Biddie McCluin","email":"bmccluin2f@wordpress.com"},
{"id":89,"name":"Ginevra Bonnesen","email":"gbonnesen2g@rambler.ru"},
{"id":90,"name":"Emiline Derington","email":"ederington2h@time.com"},
{"id":91,"name":"Krissie Roycroft","email":"kroycroft2i@vimeo.com"},
{"id":92,"name":"May Sleeny","email":"msleeny2j@nytimes.com"},
{"id":93,"name":"Kenna Chevins","email":"kchevins2k@umn.edu"},
{"id":94,"name":"Anne-marie Pegg","email":"apegg2l@csmonitor.com"},
{"id":95,"name":"Orin Ringham","email":"oringham2m@boston.com"},
{"id":96,"name":"Clarisse McCafferky","email":"cmccafferky2n@npr.org"},
{"id":97,"name":"Charmaine Rijkeseis","email":"crijkeseis2o@globo.com"},
{"id":98,"name":"Sammy Methven","email":"smethven2p@latimes.com"},
{"id":99,"name":"Milicent Stoyles","email":"mstoyles2q@cbsnews.com"},
{"id":100,"name":"Frazer Balser","email":"fbalser2r@deviantart.com"},
{"id":101,"name":"Dorelia Corselles","email":"dcorselles2s@mtv.com"},
{"id":102,"name":"Virgilio Gerling","email":"vgerling2t@goo.gl"},
{"id":103,"name":"Isahella McShea","email":"imcshea2u@bravesites.com"},
{"id":104,"name":"Thayne Rodda","email":"trodda2v@g.co"},
{"id":105,"name":"Iago Maisey","email":"imaisey2w@discuz.net"},
{"id":106,"name":"Karlene Sharple","email":"ksharple2x@walmart.com"},
{"id":107,"name":"Ernst Gauson","email":"egauson2y@webmd.com"},
{"id":108,"name":"Leoline Wanell","email":"lwanell2z@people.com.cn"},
{"id":109,"name":"Gordon Killgus","email":"gkillgus30@icio.us"},
{"id":110,"name":"Doria Jopke","email":"djopke31@reverbnation.com"},
{"id":111,"name":"Theressa Gullberg","email":"tgullberg32@homestead.com"},
{"id":112,"name":"Wanda Bewshire","email":"wbewshire33@networkadvertising.org"},
{"id":113,"name":"Dulcy Baynham","email":"dbaynham34@imgur.com"},
{"id":114,"name":"Chandler Bryenton","email":"cbryenton35@imgur.com"},
{"id":115,"name":"Archie Harmant","email":"aharmant36@histats.com"},
{"id":116,"name":"Bevvy Snoddin","email":"bsnoddin37@intel.com"},
{"id":117,"name":"Scarlet Stepney","email":"sstepney38@hud.gov"},
{"id":118,"name":"Nate Hunn","email":"nhunn39@yellowpages.com"},
{"id":119,"name":"Tierney Seaborne","email":"tseaborne3a@ustream.tv"},
{"id":120,"name":"Sawyer Ickovits","email":"sickovits3b@blogs.com"},
{"id":121,"name":"Lidia Priver","email":"lpriver3c@hp.com"},
{"id":122,"name":"Francyne Muehler","email":"fmuehler3d@yandex.ru"},
{"id":123,"name":"Roxy Freebury","email":"rfreebury3e@disqus.com"},
{"id":124,"name":"Mayne Kuscha","email":"mkuscha3f@mlb.com"},
{"id":125,"name":"Elna Beinisch","email":"ebeinisch3g@seesaa.net"},
{"id":126,"name":"Gal Melbert","email":"gmelbert3h@ihg.com"},
{"id":127,"name":"Cornall Duggary","email":"cduggary3i@utexas.edu"},
{"id":128,"name":"Lina Skeemor","email":"lskeemor3j@wikimedia.org"},
{"id":129,"name":"Immanuel Keilty","email":"ikeilty3k@stumbleupon.com"},
{"id":130,"name":"Chrystel Dauber","email":"cdauber3l@bbb.org"},
{"id":131,"name":"Blakeley Clausen","email":"bclausen3m@tuttocitta.it"},
{"id":132,"name":"Ester Bowes","email":"ebowes3n@google.nl"},
{"id":133,"name":"Fred Fownes","email":"ffownes3o@dell.com"},
{"id":134,"name":"Eddy Glidder","email":"eglidder3p@redcross.org"},
{"id":135,"name":"Ringo Jersch","email":"rjersch3q@wired.com"},
{"id":136,"name":"Maryl Shottin","email":"mshottin3r@digg.com"},
{"id":137,"name":"Dolley Wardingley","email":"dwardingley3s@booking.com"},
{"id":138,"name":"Kelley Saylor","email":"ksaylor3t@yandex.ru"},
{"id":139,"name":"Chandler Fossett","email":"cfossett3u@hud.gov"},
{"id":140,"name":"Sapphira Bennison","email":"sbennison3v@posterous.com"},
{"id":141,"name":"Bordy De Freyne","email":"bde3w@ibm.com"},
{"id":142,"name":"Freda Ledgeway","email":"fledgeway3x@discovery.com"},
{"id":143,"name":"Josh Iannitti","email":"jiannitti3y@yahoo.co.jp"},
{"id":144,"name":"Luke Sambell","email":"lsambell3z@reference.com"},
{"id":145,"name":"Lynnette Omrod","email":"lomrod40@dagondesign.com"},
{"id":146,"name":"Robers Beville","email":"rbeville41@pcworld.com"},
{"id":147,"name":"Selina Summerly","email":"ssummerly42@delicious.com"},
{"id":148,"name":"Aubree Bartos","email":"abartos43@slashdot.org"},
{"id":149,"name":"Marla Deighan","email":"mdeighan44@nba.com"},
{"id":150,"name":"Margarette Jouaneton","email":"mjouaneton45@webs.com"},
{"id":151,"name":"Daphne Drinkwater","email":"ddrinkwater46@soundcloud.com"},
{"id":152,"name":"Margette Treslove","email":"mtreslove47@amazon.de"},
{"id":153,"name":"Lauraine Berrycloth","email":"lberrycloth48@people.com.cn"},
{"id":154,"name":"Vasily Rosentholer","email":"vrosentholer49@nps.gov"},
{"id":155,"name":"Tony Pask","email":"tpask4a@goo.gl"},
{"id":156,"name":"Lindsay Pillington","email":"lpillington4b@wired.com"},
{"id":157,"name":"Thaddeus Dovey","email":"tdovey4c@foxnews.com"},
{"id":158,"name":"Karlyn Rosensaft","email":"krosensaft4d@newyorker.com"},
{"id":159,"name":"Norine Nortcliffe","email":"nnortcliffe4e@mapy.cz"},
{"id":160,"name":"Legra Cottem","email":"lcottem4f@jimdo.com"},
{"id":161,"name":"Wilt Marcome","email":"wmarcome4g@prnewswire.com"},
{"id":162,"name":"Ricard Pengilley","email":"rpengilley4h@google.cn"},
{"id":163,"name":"Rosalind Delafont","email":"rdelafont4i@jigsy.com"},
{"id":164,"name":"Dena Cohn","email":"dcohn4j@deviantart.com"},
{"id":165,"name":"Wiley Evesque","email":"wevesque4k@wiley.com"},
{"id":166,"name":"Marika Ludwell","email":"mludwell4l@japanpost.jp"},
{"id":167,"name":"Olvan Hruska","email":"ohruska4m@marketwatch.com"},
{"id":168,"name":"Mala Gadson","email":"mgadson4n@shareasale.com"},
{"id":169,"name":"Llewellyn Brewer","email":"lbrewer4o@blogtalkradio.com"},
{"id":170,"name":"Loutitia Clarage","email":"lclarage4p@hostgator.com"},
{"id":171,"name":"Jessi Newtown","email":"jnewtown4q@vkontakte.ru"},
{"id":172,"name":"Rikki McCurtain","email":"rmccurtain4r@bloglovin.com"},
{"id":173,"name":"Bastien Diaper","email":"bdiaper4s@google.com.br"},
{"id":174,"name":"Nap Calderon","email":"ncalderon4t@google.com"},
{"id":175,"name":"Lorenzo Staniford","email":"lstaniford4u@vinaora.com"},
{"id":176,"name":"Ramsay Dolle","email":"rdolle4v@delicious.com"},
{"id":177,"name":"Meridel Wogdon","email":"mwogdon4w@example.com"},
{"id":178,"name":"Bruis Carlisso","email":"bcarlisso4x@liveinternet.ru"},
{"id":179,"name":"Colline Rawls","email":"crawls4y@twitpic.com"},
{"id":180,"name":"Willy Croke","email":"wcroke4z@geocities.jp"},
{"id":181,"name":"Marilin Merrall","email":"mmerrall50@ebay.com"},
{"id":182,"name":"Skylar Pickrill","email":"spickrill51@arstechnica.com"},
{"id":183,"name":"Codie Ferdinand","email":"cferdinand52@gravatar.com"},
{"id":184,"name":"Montague Tomley","email":"mtomley53@umich.edu"},
{"id":185,"name":"Natty Clemitt","email":"nclemitt54@ezinearticles.com"},
{"id":186,"name":"Madlin Covolini","email":"mcovolini55@noaa.gov"},
{"id":187,"name":"Tristan Lantiffe","email":"tlantiffe56@aol.com"},
{"id":188,"name":"Anna-diana Bruckstein","email":"abruckstein57@1und1.de"},
{"id":189,"name":"Denni Worden","email":"dworden58@gravatar.com"},
{"id":190,"name":"Drucy Baselli","email":"dbaselli59@bbb.org"},
{"id":191,"name":"Glynn Tewkesberry","email":"gtewkesberry5a@merriam-webster.com"},
{"id":192,"name":"Corabel Fullerd","email":"cfullerd5b@dropbox.com"},
{"id":193,"name":"Catherin Mills","email":"cmills5c@imgur.com"},
{"id":194,"name":"Dell Fateley","email":"dfateley5d@state.gov"},
{"id":195,"name":"Candi Sauter","email":"csauter5e@trellian.com"},
{"id":196,"name":"Renard Moncey","email":"rmoncey5f@cbslocal.com"},
{"id":197,"name":"Carry Boddington","email":"cboddington5g@cargocollective.com"},
{"id":198,"name":"Orlan Danilchenko","email":"odanilchenko5h@epa.gov"},
{"id":199,"name":"Michele Conelly","email":"mconelly5i@wordpress.com"},
{"id":200,"name":"Maximilien Jerdein","email":"mjerdein5j@posterous.com"},
{"id":201,"name":"Anna-diana Whittington","email":"awhittington5k@nydailynews.com"},
{"id":202,"name":"Shay Blanden","email":"sblanden5l@jigsy.com"},
{"id":203,"name":"Bruis Blakiston","email":"bblakiston5m@ifeng.com"},
{"id":204,"name":"Vaughan Pitsall","email":"vpitsall5n@cisco.com"},
{"id":205,"name":"Ulla Bendare","email":"ubendare5o@exblog.jp"},
{"id":206,"name":"Evelina Roe","email":"eroe5p@mit.edu"},
{"id":207,"name":"Godfrey Botwood","email":"gbotwood5q@state.tx.us"},
{"id":208,"name":"Murry Pell","email":"mpell5r@facebook.com"},
{"id":209,"name":"Giraldo Bande","email":"gbande5s@constantcontact.com"},
{"id":210,"name":"Rhodia Whilder","email":"rwhilder5t@oracle.com"},
{"id":211,"name":"Consalve Rosenauer","email":"crosenauer5u@cam.ac.uk"},
{"id":212,"name":"Lazar Drohun","email":"ldrohun5v@cnn.com"},
{"id":213,"name":"Cathryn Yeowell","email":"cyeowell5w@chicagotribune.com"},
{"id":214,"name":"Zonnya Panting","email":"zpanting5x@msn.com"},
{"id":215,"name":"Bat Erskine","email":"berskine5y@trellian.com"},
{"id":216,"name":"Denni Penner","email":"dpenner5z@wp.com"},
{"id":217,"name":"Manon Vanetti","email":"mvanetti60@xinhuanet.com"},
{"id":218,"name":"Vidovic Aymes","email":"vaymes61@istockphoto.com"},
{"id":219,"name":"Ives Peachey","email":"ipeachey62@ebay.com"},
{"id":220,"name":"Rici Batt","email":"rbatt63@nba.com"},
{"id":221,"name":"Pen Nesbitt","email":"pnesbitt64@dagondesign.com"},
{"id":222,"name":"Svend Espada","email":"sespada65@hhs.gov"},
{"id":223,"name":"Rafferty Bruhnke","email":"rbruhnke66@vinaora.com"},
{"id":224,"name":"Orrin Walkden","email":"owalkden67@tmall.com"},
{"id":225,"name":"Joyann Mariette","email":"jmariette68@acquirethisname.com"},
{"id":226,"name":"Evangelia Dimbylow","email":"edimbylow69@bloglines.com"},
{"id":227,"name":"Kristofer Thying","email":"kthying6a@livejournal.com"},
{"id":228,"name":"Dorri Fennessy","email":"dfennessy6b@hc360.com"},
{"id":229,"name":"Abramo Eliet","email":"aeliet6c@xrea.com"},
{"id":230,"name":"Blinni Dallan","email":"bdallan6d@diigo.com"},
{"id":231,"name":"Ewen Pizey","email":"epizey6e@springer.com"},
{"id":232,"name":"Lawry Barfford","email":"lbarfford6f@google.de"},
{"id":233,"name":"Lukas O'Scollain","email":"loscollain6g@simplemachines.org"},
{"id":234,"name":"Rosina Adolphine","email":"radolphine6h@acquirethisname.com"},
{"id":235,"name":"Giraldo Corbin","email":"gcorbin6i@free.fr"},
{"id":236,"name":"Hussein Appleyard","email":"happleyard6j@guardian.co.uk"},
{"id":237,"name":"Kaycee Prier","email":"kprier6k@walmart.com"},
{"id":238,"name":"Rhonda Smuth","email":"rsmuth6l@time.com"},
{"id":239,"name":"Ninette Elcoate","email":"nelcoate6m@ehow.com"},
{"id":240,"name":"Ezechiel Oxlade","email":"eoxlade6n@craigslist.org"},
{"id":241,"name":"Bronnie Lambal","email":"blambal6o@google.pl"},
{"id":242,"name":"Herc Dillinton","email":"hdillinton6p@indiatimes.com"},
{"id":243,"name":"Mignon Stockney","email":"mstockney6q@a8.net"},
{"id":244,"name":"Ronda Hebron","email":"rhebron6r@wsj.com"},
{"id":245,"name":"Marni Rudderham","email":"mrudderham6s@tripadvisor.com"},
{"id":246,"name":"Sile Kermannes","email":"skermannes6t@prnewswire.com"},
{"id":247,"name":"Ashla Abdy","email":"aabdy6u@wunderground.com"},
{"id":248,"name":"Chance Chalmers","email":"cchalmers6v@google.nl"},
{"id":249,"name":"Inge Pesselt","email":"ipesselt6w@globo.com"},
{"id":250,"name":"Hasheem MacSweeney","email":"hmacsweeney6x@comcast.net"},
{"id":251,"name":"Brantley Fosh","email":"bfosh6y@opera.com"},
{"id":252,"name":"Priscella Lydiatt","email":"plydiatt6z@pen.io"},
{"id":253,"name":"Laurel Coston","email":"lcoston70@netvibes.com"},
{"id":254,"name":"Jaquelyn Riteley","email":"jriteley71@imageshack.us"},
{"id":255,"name":"Alexis Rattry","email":"arattry72@mozilla.org"},
{"id":256,"name":"Erl Patrickson","email":"epatrickson73@microsoft.com"},
{"id":257,"name":"Aeriell Stammirs","email":"astammirs74@mac.com"},
{"id":258,"name":"Gery Hallam","email":"ghallam75@ft.com"},
{"id":259,"name":"Fons Hing","email":"fhing76@rakuten.co.jp"},
{"id":260,"name":"Deane Fairbrace","email":"dfairbrace77@webs.com"},
{"id":261,"name":"Rosemarie Glanister","email":"rglanister78@amazon.co.jp"},
{"id":262,"name":"Nelia Winter","email":"nwinter79@ucoz.com"},
{"id":263,"name":"Barth Wogdon","email":"bwogdon7a@webs.com"},
{"id":264,"name":"Shannan Poxson","email":"spoxson7b@webnode.com"},
{"id":265,"name":"Nolan Nutting","email":"nnutting7c@hibu.com"},
{"id":266,"name":"Adore Smitheman","email":"asmitheman7d@google.it"},
{"id":267,"name":"Edik Elwin","email":"eelwin7e@infoseek.co.jp"},
{"id":268,"name":"Veronique Tippings","email":"vtippings7f@statcounter.com"},
{"id":269,"name":"Inez Badsey","email":"ibadsey7g@unicef.org"},
{"id":270,"name":"Dudley Couling","email":"dcouling7h@hexun.com"},
{"id":271,"name":"Bee Sharphouse","email":"bsharphouse7i@cbc.ca"},
{"id":272,"name":"Jessee Durham","email":"jdurham7j@ezinearticles.com"},
{"id":273,"name":"Orv Boustred","email":"oboustred7k@1688.com"},
{"id":274,"name":"Ike Dyster","email":"idyster7l@gnu.org"},
{"id":275,"name":"Tallie Burry","email":"tburry7m@wiley.com"},
{"id":276,"name":"Darsey Craister","email":"dcraister7n@scribd.com"},
{"id":277,"name":"Colene Barthelemy","email":"cbarthelemy7o@gnu.org"},
{"id":278,"name":"Creigh Bampkin","email":"cbampkin7p@google.pl"},
{"id":279,"name":"Margareta Brawson","email":"mbrawson7q@booking.com"},
{"id":280,"name":"Curry Tunbridge","email":"ctunbridge7r@trellian.com"},
{"id":281,"name":"Rosette Bullas","email":"rbullas7s@boston.com"},
{"id":282,"name":"Malory Mort","email":"mmort7t@uiuc.edu"},
{"id":283,"name":"Ogdon Fabry","email":"ofabry7u@acquirethisname.com"},
{"id":284,"name":"Laure Coldrick","email":"lcoldrick7v@unesco.org"},
{"id":285,"name":"Robbyn Alman","email":"ralman7w@addthis.com"},
{"id":286,"name":"Felicdad Cahani","email":"fcahani7x@furl.net"},
{"id":287,"name":"Harriott Loghan","email":"hloghan7y@miitbeian.gov.cn"},
{"id":288,"name":"Barby Faley","email":"bfaley7z@barnesandnoble.com"},
{"id":289,"name":"Reinhold Sellek","email":"rsellek80@redcross.org"},
{"id":290,"name":"Harriot Sycamore","email":"hsycamore81@163.com"},
{"id":291,"name":"Lynea Earwicker","email":"learwicker82@blogtalkradio.com"},
{"id":292,"name":"Glennie McKinney","email":"gmckinney83@meetup.com"},
{"id":293,"name":"Pepe Pouton","email":"ppouton84@a8.net"},
{"id":294,"name":"Agata O'Dougherty","email":"aodougherty85@gov.uk"},
{"id":295,"name":"Mariam Sutworth","email":"msutworth86@lulu.com"},
{"id":296,"name":"Luce Garvie","email":"lgarvie87@networksolutions.com"},
{"id":297,"name":"Ailsun Dmisek","email":"admisek88@state.gov"},
{"id":298,"name":"Idaline McGahey","email":"imcgahey89@blog.com"},
{"id":299,"name":"Jessamyn Insley","email":"jinsley8a@ibm.com"},
{"id":300,"name":"Evelina Dewi","email":"edewi8b@apache.org"},
{"id":301,"name":"Margit Abthorpe","email":"mabthorpe8c@nps.gov"},
{"id":302,"name":"Stefan Cleobury","email":"scleobury8d@privacy.gov.au"},
{"id":303,"name":"Trixy Liquorish","email":"tliquorish8e@home.pl"},
{"id":304,"name":"Seumas Scrange","email":"sscrange8f@amazon.co.uk"},
{"id":305,"name":"Pooh Emms","email":"pemms8g@ebay.co.uk"},
{"id":306,"name":"Bernita Doumic","email":"bdoumic8h@blogs.com"},
{"id":307,"name":"Casi Stretton","email":"cstretton8i@flavors.me"},
{"id":308,"name":"Analise Simmings","email":"asimmings8j@soundcloud.com"},
{"id":309,"name":"Tarah Lambrecht","email":"tlambrecht8k@dyndns.org"},
{"id":310,"name":"Sandro Episcopi","email":"sepiscopi8l@umn.edu"},
{"id":311,"name":"Allie Dawkins","email":"adawkins8m@multiply.com"},
{"id":312,"name":"Tabatha Goodhay","email":"tgoodhay8n@foxnews.com"},
{"id":313,"name":"Ange Badgers","email":"abadgers8o@unc.edu"},
{"id":314,"name":"Waring Ladd","email":"wladd8p@phpbb.com"},
{"id":315,"name":"Lorenzo Allsupp","email":"lallsupp8q@comsenz.com"},
{"id":316,"name":"Tristan Corragan","email":"tcorragan8r@a8.net"},
{"id":317,"name":"Noll Knappett","email":"nknappett8s@independent.co.uk"},
{"id":318,"name":"Hall Monsey","email":"hmonsey8t@a8.net"},
{"id":319,"name":"Reeba Kesby","email":"rkesby8u@theguardian.com"},
{"id":320,"name":"Jo Hunnawill","email":"jhunnawill8v@bizjournals.com"},
{"id":321,"name":"Tim Pote","email":"tpote8w@wix.com"},
{"id":322,"name":"Rainer Brassington","email":"rbrassington8x@paypal.com"},
{"id":323,"name":"Shayna Graybeal","email":"sgraybeal8y@huffingtonpost.com"},
{"id":324,"name":"Heddie Tuffell","email":"htuffell8z@gravatar.com"},
{"id":325,"name":"Bernie Kenworth","email":"bkenworth90@sun.com"},
{"id":326,"name":"Robinet Huxley","email":"rhuxley91@github.com"},
{"id":327,"name":"Mattie Brisse","email":"mbrisse92@usgs.gov"},
{"id":328,"name":"Fonz Jolland","email":"fjolland93@123-reg.co.uk"},
{"id":329,"name":"Winn Covell","email":"wcovell94@indiegogo.com"},
{"id":330,"name":"Frasco Gammack","email":"fgammack95@vk.com"},
{"id":331,"name":"Dennis Reek","email":"dreek96@dailymotion.com"},
{"id":332,"name":"Kent Gethin","email":"kgethin97@time.com"},
{"id":333,"name":"Tessa Kalinsky","email":"tkalinsky98@hubpages.com"},
{"id":334,"name":"Stefano Dimbleby","email":"sdimbleby99@storify.com"},
{"id":335,"name":"Margarete Pawling","email":"mpawling9a@xinhuanet.com"},
{"id":336,"name":"Gabbie Dunnaway","email":"gdunnaway9b@tuttocitta.it"},
{"id":337,"name":"Lars Pickhaver","email":"lpickhaver9c@ucoz.com"},
{"id":338,"name":"Rad Deighan","email":"rdeighan9d@uiuc.edu"},
{"id":339,"name":"Holly-anne Gariff","email":"hgariff9e@odnoklassniki.ru"},
{"id":340,"name":"Evyn Breming","email":"ebreming9f@boston.com"},
{"id":341,"name":"Patricia Trodd","email":"ptrodd9g@indiegogo.com"},
{"id":342,"name":"Bernadina Yuranovev","email":"byuranovev9h@pbs.org"},
{"id":343,"name":"Felipa Turone","email":"fturone9i@blinklist.com"},
{"id":344,"name":"Farand Veneur","email":"fveneur9j@businessinsider.com"},
{"id":345,"name":"Fiann Keats","email":"fkeats9k@mysql.com"},
{"id":346,"name":"Jojo Swatland","email":"jswatland9l@sitemeter.com"},
{"id":347,"name":"Gan Winslet","email":"gwinslet9m@deviantart.com"},
{"id":348,"name":"Krishnah Sevior","email":"ksevior9n@harvard.edu"},
{"id":349,"name":"Rodie Headland","email":"rheadland9o@washingtonpost.com"},
{"id":350,"name":"Armstrong Kearley","email":"akearley9p@ox.ac.uk"},
{"id":351,"name":"Moshe Chiechio","email":"mchiechio9q@edublogs.org"},
{"id":352,"name":"Abram Cricket","email":"acricket9r@usgs.gov"},
{"id":353,"name":"Sheffield Blanshard","email":"sblanshard9s@hao123.com"},
{"id":354,"name":"Ruddie Dohr","email":"rdohr9t@samsung.com"},
{"id":355,"name":"Ange Atmore","email":"aatmore9u@github.io"},
{"id":356,"name":"Kristy Corah","email":"kcorah9v@samsung.com"},
{"id":357,"name":"Engelbert Abrahamsen","email":"eabrahamsen9w@ucsd.edu"},
{"id":358,"name":"Doro Bacon","email":"dbacon9x@indiatimes.com"},
{"id":359,"name":"Cyndia Bahls","email":"cbahls9y@mashable.com"},
{"id":360,"name":"Hazel Standish-Brooks","email":"hstandishbrooks9z@engadget.com"},
{"id":361,"name":"Rica English","email":"renglisha0@army.mil"},
{"id":362,"name":"Winny Furbank","email":"wfurbanka1@twitpic.com"},
{"id":363,"name":"Wilmette Bethune","email":"wbethunea2@irs.gov"},
{"id":364,"name":"Eileen Joannet","email":"ejoanneta3@dedecms.com"},
{"id":365,"name":"Ashia Bonde","email":"abondea4@yellowbook.com"},
{"id":366,"name":"Wally Hymer","email":"whymera5@gmpg.org"},
{"id":367,"name":"Gui Schlagtmans","email":"gschlagtmansa6@aol.com"},
{"id":368,"name":"Tommie Frie","email":"tfriea7@jimdo.com"},
{"id":369,"name":"Ezequiel Brandrick","email":"ebrandricka8@oakley.com"},
{"id":370,"name":"Esme Clissell","email":"eclissella9@admin.ch"},
{"id":371,"name":"Ethelyn Twoohy","email":"etwoohyaa@sphinn.com"},
{"id":372,"name":"Larine Orkney","email":"lorkneyab@geocities.jp"},
{"id":373,"name":"Jone Rosenstiel","email":"jrosenstielac@globo.com"},
{"id":374,"name":"Chicky Wreakes","email":"cwreakesad@digg.com"},
{"id":375,"name":"Chantal Locker","email":"clockerae@umich.edu"},
{"id":376,"name":"Berry Hardage","email":"bhardageaf@cpanel.net"},
{"id":377,"name":"Milty Maasz","email":"mmaaszag@w3.org"},
{"id":378,"name":"Jeffrey Ruggiero","email":"jruggieroah@nhs.uk"},
{"id":379,"name":"Archer Pawley","email":"apawleyai@ask.com"},
{"id":380,"name":"Ginelle Metzig","email":"gmetzigaj@weather.com"},
{"id":381,"name":"Bobbie Ivermee","email":"bivermeeak@uiuc.edu"},
{"id":382,"name":"Jenelle Tarply","email":"jtarplyal@seattletimes.com"},
{"id":383,"name":"Benjamin Hanner","email":"bhanneram@bigcartel.com"},
{"id":384,"name":"Ebeneser Umbert","email":"eumbertan@webnode.com"},
{"id":385,"name":"Eberto Howselee","email":"ehowseleeao@php.net"},
{"id":386,"name":"Morrie Mathewson","email":"mmathewsonap@artisteer.com"},
{"id":387,"name":"Veda Jewes","email":"vjewesaq@unesco.org"},
{"id":388,"name":"Randie Newis","email":"rnewisar@bluehost.com"},
{"id":389,"name":"Fraze MacSween","email":"fmacsweenas@census.gov"},
{"id":390,"name":"Tammie Filippi","email":"tfilippiat@imageshack.us"},
{"id":391,"name":"Seka Vann","email":"svannau@taobao.com"},
{"id":392,"name":"Jacinta Helversen","email":"jhelversenav@vkontakte.ru"},
{"id":393,"name":"Afton Malthus","email":"amalthusaw@house.gov"},
{"id":394,"name":"Celestyna Miquelet","email":"cmiqueletax@dailymail.co.uk"},
{"id":395,"name":"Vivyanne Mottershaw","email":"vmottershaway@nyu.edu"},
{"id":396,"name":"Dalia Sieghard","email":"dsieghardaz@godaddy.com"},
{"id":397,"name":"Avril Battaille","email":"abattailleb0@oaic.gov.au"},
{"id":398,"name":"Doria Pauletto","email":"dpaulettob1@wikimedia.org"},
{"id":399,"name":"Devin Theuss","email":"dtheussb2@va.gov"},
{"id":400,"name":"Ronna Smithen","email":"rsmithenb3@squidoo.com"},
{"id":401,"name":"Nilson Zanelli","email":"nzanellib4@marketwatch.com"},
{"id":402,"name":"Abran Nickerson","email":"anickersonb5@ameblo.jp"},
{"id":403,"name":"Rosalind Stock","email":"rstockb6@scientificamerican.com"},
{"id":404,"name":"Ariel Cashell","email":"acashellb7@odnoklassniki.ru"},
{"id":405,"name":"Bealle Doring","email":"bdoringb8@ameblo.jp"},
{"id":406,"name":"Jean Rentilll","email":"jrentilllb9@google.com.br"},
{"id":407,"name":"Darrick Filipczynski","email":"dfilipczynskiba@ehow.com"},
{"id":408,"name":"Teodora Marklin","email":"tmarklinbb@geocities.com"},
{"id":409,"name":"Helyn Byles","email":"hbylesbc@hao123.com"},
{"id":410,"name":"Wolfgang Kleint","email":"wkleintbd@domainmarket.com"},
{"id":411,"name":"Malina Moncrieffe","email":"mmoncrieffebe@blogtalkradio.com"},
{"id":412,"name":"Ashbey Realy","email":"arealybf@naver.com"},
{"id":413,"name":"Trudi Colthard","email":"tcolthardbg@wp.com"},
{"id":414,"name":"Cammie Hellsdon","email":"chellsdonbh@dropbox.com"},
{"id":415,"name":"Wynnie Jaram","email":"wjarambi@howstuffworks.com"},
{"id":416,"name":"Spenser Lorain","email":"slorainbj@netlog.com"},
{"id":417,"name":"Bronson Seine","email":"bseinebk@wired.com"},
{"id":418,"name":"Ulrike Smallpeice","email":"usmallpeicebl@networksolutions.com"},
{"id":419,"name":"Munroe Cossins","email":"mcossinsbm@imageshack.us"},
{"id":420,"name":"Amber Jenicke","email":"ajenickebn@army.mil"},
{"id":421,"name":"Caryl Cosgreave","email":"ccosgreavebo@sohu.com"},
{"id":422,"name":"Nickolai Newling","email":"nnewlingbp@howstuffworks.com"},
{"id":423,"name":"Nadeen Gockelen","email":"ngockelenbq@toplist.cz"},
{"id":424,"name":"Crista Haskew","email":"chaskewbr@ed.gov"},
{"id":425,"name":"Jasmin McNess","email":"jmcnessbs@cornell.edu"},
{"id":426,"name":"Maurice Kembley","email":"mkembleybt@so-net.ne.jp"},
{"id":427,"name":"Corie Murname","email":"cmurnamebu@de.vu"},
{"id":428,"name":"Annie Grason","email":"agrasonbv@epa.gov"},
{"id":429,"name":"Erhard Wearing","email":"ewearingbw@example.com"},
{"id":430,"name":"Consalve Billings","email":"cbillingsbx@squidoo.com"},
{"id":431,"name":"Damaris Oubridge","email":"doubridgeby@a8.net"},
{"id":432,"name":"Kennith Lacey","email":"klaceybz@patch.com"},
{"id":433,"name":"Lemmie Cavnor","email":"lcavnorc0@house.gov"},
{"id":434,"name":"Hedwig Walduck","email":"hwalduckc1@ftc.gov"},
{"id":435,"name":"Nicole Rouzet","email":"nrouzetc2@fda.gov"},
{"id":436,"name":"Micah Sellner","email":"msellnerc3@earthlink.net"},
{"id":437,"name":"Trudie Davoren","email":"tdavorenc4@cloudflare.com"},
{"id":438,"name":"Lucho Grunnill","email":"lgrunnillc5@unicef.org"},
{"id":439,"name":"Ellis Neagle","email":"eneaglec6@comsenz.com"},
{"id":440,"name":"Jsandye Harmer","email":"jharmerc7@linkedin.com"},
{"id":441,"name":"Rainer Raddenbury","email":"rraddenburyc8@meetup.com"},
{"id":442,"name":"Desiree Shatliffe","email":"dshatliffec9@sun.com"},
{"id":443,"name":"Debee Isworth","email":"disworthca@thetimes.co.uk"},
{"id":444,"name":"Demetris Houliston","email":"dhoulistoncb@opera.com"},
{"id":445,"name":"Beulah Humblestone","email":"bhumblestonecc@feedburner.com"},
{"id":446,"name":"Nappy Smythin","email":"nsmythincd@intel.com"},
{"id":447,"name":"Helli Seiler","email":"hseilerce@amazonaws.com"},
{"id":448,"name":"Andie Krystof","email":"akrystofcf@1688.com"},
{"id":449,"name":"Yvon Matthiesen","email":"ymatthiesencg@nps.gov"},
{"id":450,"name":"Janis Rouke","email":"jroukech@nasa.gov"},
{"id":451,"name":"Freddy Lorryman","email":"florrymanci@stanford.edu"},
{"id":452,"name":"Susi Kender","email":"skendercj@archive.org"},
{"id":453,"name":"Yolanda Shadfourth","email":"yshadfourthck@ibm.com"},
{"id":454,"name":"Borg Van der Krui","email":"bvancl@ask.com"},
{"id":455,"name":"Deloria Philipet","email":"dphilipetcm@narod.ru"},
{"id":456,"name":"Koral Candy","email":"kcandycn@infoseek.co.jp"},
{"id":457,"name":"Lorrie Janaszkiewicz","email":"ljanaszkiewiczco@sun.com"},
{"id":458,"name":"Anallese Gerrill","email":"agerrillcp@google.es"},
{"id":459,"name":"Gallagher Chuter","email":"gchutercq@stumbleupon.com"},
{"id":460,"name":"Holly Weatherall","email":"hweatherallcr@free.fr"},
{"id":461,"name":"Delphine Beades","email":"dbeadescs@samsung.com"},
{"id":462,"name":"Ellissa House","email":"ehousect@php.net"},
{"id":463,"name":"Marwin Skarin","email":"mskarincu@homestead.com"},
{"id":464,"name":"Kerrie Powderham","email":"kpowderhamcv@unblog.fr"},
{"id":465,"name":"Shaina Upshall","email":"supshallcw@kickstarter.com"},
{"id":466,"name":"Devina McGhee","email":"dmcgheecx@histats.com"},
{"id":467,"name":"Allyn Alesio","email":"aalesiocy@ycombinator.com"},
{"id":468,"name":"Bianca Marzelle","email":"bmarzellecz@istockphoto.com"},
{"id":469,"name":"Mariska Tommasuzzi","email":"mtommasuzzid0@shop-pro.jp"},
{"id":470,"name":"Yoshi Hannay","email":"yhannayd1@tripod.com"},
{"id":471,"name":"Heda Chazerand","email":"hchazerandd2@msn.com"},
{"id":472,"name":"Logan Ealam","email":"lealamd3@ustream.tv"},
{"id":473,"name":"Maria Wreath","email":"mwreathd4@people.com.cn"},
{"id":474,"name":"Taddeo Misselbrook","email":"tmisselbrookd5@hibu.com"},
{"id":475,"name":"Upton Aireton","email":"uairetond6@gravatar.com"},
{"id":476,"name":"Normie Keyho","email":"nkeyhod7@biblegateway.com"},
{"id":477,"name":"Bradley Benfield","email":"bbenfieldd8@bluehost.com"},
{"id":478,"name":"Crissy Pietrzak","email":"cpietrzakd9@buzzfeed.com"},
{"id":479,"name":"Celle Barmadier","email":"cbarmadierda@moonfruit.com"},
{"id":480,"name":"Chan Grece","email":"cgrecedb@sina.com.cn"},
{"id":481,"name":"Ferrell Perrottet","email":"fperrottetdc@plala.or.jp"},
{"id":482,"name":"Valina McKnish","email":"vmcknishdd@mayoclinic.com"},
{"id":483,"name":"Abigale Heinert","email":"aheinertde@ucla.edu"},
{"id":484,"name":"Dolorita Kleinstein","email":"dkleinsteindf@simplemachines.org"},
{"id":485,"name":"Mirelle Schoales","email":"mschoalesdg@desdev.cn"},
{"id":486,"name":"Jacquenette Verden","email":"jverdendh@gov.uk"},
{"id":487,"name":"Moria Ravenshear","email":"mravensheardi@uiuc.edu"},
{"id":488,"name":"Pepillo Kerss","email":"pkerssdj@dailymotion.com"},
{"id":489,"name":"Mick Lissandrini","email":"mlissandrinidk@addthis.com"},
{"id":490,"name":"Winny Woodier","email":"wwoodierdl@newyorker.com"},
{"id":491,"name":"Nettle Demangeot","email":"ndemangeotdm@gnu.org"},
{"id":492,"name":"Juliana Bilbrooke","email":"jbilbrookedn@jugem.jp"},
{"id":493,"name":"Callida Garnsworth","email":"cgarnsworthdo@google.com.au"},
{"id":494,"name":"Cordy Chattey","email":"cchatteydp@biblegateway.com"},
{"id":495,"name":"Sondra Swinden","email":"sswindendq@mashable.com"},
{"id":496,"name":"Tanhya Kennedy","email":"tkennedydr@constantcontact.com"},
{"id":497,"name":"Victor Cooke","email":"vcookeds@wikispaces.com"},
{"id":498,"name":"Bax Bowen","email":"bbowendt@drupal.org"},
{"id":499,"name":"Libbie Biever","email":"lbieverdu@newsvine.com"},
{"id":500,"name":"Lenci Slayny","email":"lslaynydv@webeden.co.uk"},
{"id":501,"name":"Micki Rudall","email":"mrudalldw@house.gov"},
{"id":502,"name":"Chris Waywell","email":"cwaywelldx@toplist.cz"},
{"id":503,"name":"Lynn Durgan","email":"ldurgandy@theglobeandmail.com"},
{"id":504,"name":"Midge Jefferson","email":"mjeffersondz@g.co"},
{"id":505,"name":"Maximilianus Wank","email":"mwanke0@toplist.cz"},
{"id":506,"name":"Leontine Radenhurst","email":"lradenhurste1@aol.com"},
{"id":507,"name":"Gert La Vigne","email":"glae2@github.com"},
{"id":508,"name":"Vladamir O'Dempsey","email":"vodempseye3@themeforest.net"},
{"id":509,"name":"Oralee Mitchard","email":"omitcharde4@bandcamp.com"},
{"id":510,"name":"Margaux Conahy","email":"mconahye5@cdbaby.com"},
{"id":511,"name":"Johanna Boards","email":"jboardse6@telegraph.co.uk"},
{"id":512,"name":"Galvin Westphalen","email":"gwestphalene7@xing.com"},
{"id":513,"name":"Christa Speke","email":"cspekee8@printfriendly.com"},
{"id":514,"name":"Minny Shakespeare","email":"mshakespearee9@shop-pro.jp"},
{"id":515,"name":"Ebonee Kleewein","email":"ekleeweinea@icq.com"},
{"id":516,"name":"Eda Simkovich","email":"esimkovicheb@yellowbook.com"},
{"id":517,"name":"Franky Higgen","email":"fhiggenec@desdev.cn"},
{"id":518,"name":"Keeley Jolliman","email":"kjollimaned@npr.org"},
{"id":519,"name":"Susie Gravie","email":"sgravieee@amazon.co.uk"},
{"id":520,"name":"Philip Gaitone","email":"pgaitoneef@wunderground.com"},
{"id":521,"name":"Filmer Phateplace","email":"fphateplaceeg@yelp.com"},
{"id":522,"name":"Randene Tomasian","email":"rtomasianeh@psu.edu"},
{"id":523,"name":"Chad Broomer","email":"cbroomerei@photobucket.com"},
{"id":524,"name":"Yovonnda Sedge","email":"ysedgeej@washingtonpost.com"},
{"id":525,"name":"Roana Newens","email":"rnewensek@jimdo.com"},
{"id":526,"name":"Livia Ramsey","email":"lramseyel@weather.com"},
{"id":527,"name":"Sonya Kirkland","email":"skirklandem@yolasite.com"},
{"id":528,"name":"Maighdiln Manilo","email":"mmaniloen@jiathis.com"},
{"id":529,"name":"Rayner Rouse","email":"rrouseeo@marketwatch.com"},
{"id":530,"name":"Urbain O'Cosgra","email":"uocosgraep@artisteer.com"},
{"id":531,"name":"Marylou Balcers","email":"mbalcerseq@ftc.gov"},
{"id":532,"name":"Marget Fulleylove","email":"mfulleyloveer@weibo.com"},
{"id":533,"name":"Rick Abley","email":"rableyes@instagram.com"},
{"id":534,"name":"Abigail McNeilly","email":"amcneillyet@springer.com"},
{"id":535,"name":"Gran Pelchat","email":"gpelchateu@miitbeian.gov.cn"},
{"id":536,"name":"Melissa McKaile","email":"mmckaileev@mediafire.com"},
{"id":537,"name":"Shelba Leverette","email":"sleveretteew@unicef.org"},
{"id":538,"name":"Josh Ganing","email":"jganingex@facebook.com"},
{"id":539,"name":"Elinor Kitt","email":"ekittey@squarespace.com"},
{"id":540,"name":"Athene Trippack","email":"atrippackez@jiathis.com"},
{"id":541,"name":"Creighton Danet","email":"cdanetf0@sun.com"},
{"id":542,"name":"Margarita Camoys","email":"mcamoysf1@ebay.com"},
{"id":543,"name":"Margy MacShane","email":"mmacshanef2@whitehouse.gov"},
{"id":544,"name":"Shelly Carlon","email":"scarlonf3@rambler.ru"},
{"id":545,"name":"Barnebas Crumly","email":"bcrumlyf4@reuters.com"},
{"id":546,"name":"Jorge Portriss","email":"jportrissf5@bloglines.com"},
{"id":547,"name":"Shermy Sumnall","email":"ssumnallf6@cnet.com"},
{"id":548,"name":"Tatum Achurch","email":"tachurchf7@squarespace.com"},
{"id":549,"name":"Lowell Brownbill","email":"lbrownbillf8@facebook.com"},
{"id":550,"name":"Beverlee Kort","email":"bkortf9@tamu.edu"},
{"id":551,"name":"Nestor Baglin","email":"nbaglinfa@soup.io"},
{"id":552,"name":"Rafaelia Almack","email":"ralmackfb@webnode.com"},
{"id":553,"name":"Jacinda Ziemsen","email":"jziemsenfc@house.gov"},
{"id":554,"name":"Jocelin Jarville","email":"jjarvillefd@arstechnica.com"},
{"id":555,"name":"Lucas McReath","email":"lmcreathfe@imdb.com"},
{"id":556,"name":"Brannon Ioselev","email":"bioselevff@mit.edu"},
{"id":557,"name":"Gilberte Yewman","email":"gyewmanfg@bandcamp.com"},
{"id":558,"name":"Lacee Rapelli","email":"lrapellifh@google.es"},
{"id":559,"name":"Antonio Purrier","email":"apurrierfi@paginegialle.it"},
{"id":560,"name":"Trixi Piwell","email":"tpiwellfj@macromedia.com"},
{"id":561,"name":"Kendell Crosi","email":"kcrosifk@mac.com"},
{"id":562,"name":"Stanislaus Diviny","email":"sdivinyfl@flavors.me"},
{"id":563,"name":"Holli O'Neary","email":"honearyfm@tamu.edu"},
{"id":564,"name":"Denys Northfield","email":"dnorthfieldfn@who.int"},
{"id":565,"name":"Heywood Longrigg","email":"hlongriggfo@sciencedaily.com"},
{"id":566,"name":"Mae Kob","email":"mkobfp@homestead.com"},
{"id":567,"name":"Elsi Oakland","email":"eoaklandfq@washingtonpost.com"},
{"id":568,"name":"Shannon Allcock","email":"sallcockfr@mail.ru"},
{"id":569,"name":"Elroy Langlais","email":"elanglaisfs@unicef.org"},
{"id":570,"name":"Dione Marqyes","email":"dmarqyesft@studiopress.com"},
{"id":571,"name":"Opaline Briston","email":"obristonfu@opera.com"},
{"id":572,"name":"Emmalynn Blanc","email":"eblancfv@soundcloud.com"},
{"id":573,"name":"Hubert Sarson","email":"hsarsonfw@blogtalkradio.com"},
{"id":574,"name":"Gareth Brounsell","email":"gbrounsellfx@google.fr"},
{"id":575,"name":"Arabele Haggus","email":"ahaggusfy@cornell.edu"},
{"id":576,"name":"Heath Gready","email":"hgreadyfz@pcworld.com"},
{"id":577,"name":"Kayla Randales","email":"krandalesg0@ca.gov"},
{"id":578,"name":"Gard Ogles","email":"goglesg1@163.com"},
{"id":579,"name":"Guss Moxley","email":"gmoxleyg2@vkontakte.ru"},
{"id":580,"name":"Curtis Swindley","email":"cswindleyg3@t-online.de"},
{"id":581,"name":"Beilul Larrie","email":"blarrieg4@mozilla.org"},
{"id":582,"name":"Mitchel Ragless","email":"mraglessg5@shutterfly.com"},
{"id":583,"name":"Walker Arnke","email":"warnkeg6@booking.com"},
{"id":584,"name":"Cherice Siviter","email":"csiviterg7@amazon.co.uk"},
{"id":585,"name":"Merill Alastair","email":"malastairg8@ifeng.com"},
{"id":586,"name":"Maryanna Mewha","email":"mmewhag9@dailymotion.com"},
{"id":587,"name":"Starlin Levay","email":"slevayga@wired.com"},
{"id":588,"name":"Gerry Tafani","email":"gtafanigb@sphinn.com"},
{"id":589,"name":"Reid Figura","email":"rfiguragc@goo.gl"},
{"id":590,"name":"Starr Whiteside","email":"swhitesidegd@wufoo.com"},
{"id":591,"name":"Lydia Slesser","email":"lslesserge@last.fm"},
{"id":592,"name":"Rosaleen Ponder","email":"rpondergf@cbc.ca"},
{"id":593,"name":"Maggie Pitcher","email":"mpitchergg@xrea.com"},
{"id":594,"name":"Dalli Lloyds","email":"dlloydsgh@cbsnews.com"},
{"id":595,"name":"Karla Rawles","email":"krawlesgi@vimeo.com"},
{"id":596,"name":"Candy Mackerel","email":"cmackerelgj@hatena.ne.jp"},
{"id":597,"name":"Mohammed Tytler","email":"mtytlergk@flickr.com"},
{"id":598,"name":"Taddeo Liebmann","email":"tliebmanngl@digg.com"},
{"id":599,"name":"Chev Troak","email":"ctroakgm@dailymotion.com"},
{"id":600,"name":"Randal Bollins","email":"rbollinsgn@cnn.com"},
{"id":601,"name":"Cleo Crellim","email":"ccrellimgo@independent.co.uk"},
{"id":602,"name":"Henri Nutter","email":"hnuttergp@europa.eu"},
{"id":603,"name":"Fielding Kleine","email":"fkleinegq@so-net.ne.jp"},
{"id":604,"name":"Phaedra Di Antonio","email":"pdigr@zdnet.com"},
{"id":605,"name":"Brenden Pendergrast","email":"bpendergrastgs@cafepress.com"},
{"id":606,"name":"Myrah Petrelli","email":"mpetrelligt@creativecommons.org"},
{"id":607,"name":"Sloane Brigginshaw","email":"sbrigginshawgu@i2i.jp"},
{"id":608,"name":"Hagen Scorrer","email":"hscorrergv@imdb.com"},
{"id":609,"name":"Felisha Botterman","email":"fbottermangw@dropbox.com"},
{"id":610,"name":"Geri Meader","email":"gmeadergx@nps.gov"},
{"id":611,"name":"Angy Wolledge","email":"awolledgegy@elegantthemes.com"},
{"id":612,"name":"Reed Wrettum","email":"rwrettumgz@jimdo.com"},
{"id":613,"name":"Peirce Gabriely","email":"pgabrielyh0@nasa.gov"},
{"id":614,"name":"Alejandra Yesinin","email":"ayesininh1@spotify.com"},
{"id":615,"name":"Carrissa Fanning","email":"cfanningh2@prnewswire.com"},
{"id":616,"name":"Maddi Coath","email":"mcoathh3@goo.ne.jp"},
{"id":617,"name":"Noam Greim","email":"ngreimh4@dailymail.co.uk"},
{"id":618,"name":"Brenn Gradwell","email":"bgradwellh5@weebly.com"},
{"id":619,"name":"Brenda Glasby","email":"bglasbyh6@ed.gov"},
{"id":620,"name":"Corena Comino","email":"ccominoh7@spotify.com"},
{"id":621,"name":"Brennen Huxter","email":"bhuxterh8@ask.com"},
{"id":622,"name":"Allayne Rymill","email":"arymillh9@symantec.com"},
{"id":623,"name":"Sky Ceresa","email":"sceresaha@360.cn"},
{"id":624,"name":"Northrup Rannells","email":"nrannellshb@utexas.edu"},
{"id":625,"name":"Remington Pearton","email":"rpeartonhc@cnbc.com"},
{"id":626,"name":"Shane Cundict","email":"scundicthd@usda.gov"},
{"id":627,"name":"Demott Biernacki","email":"dbiernackihe@wp.com"},
{"id":628,"name":"Reilly Alexandersson","email":"ralexanderssonhf@nydailynews.com"},
{"id":629,"name":"Leda Kenshole","email":"lkensholehg@smugmug.com"},
{"id":630,"name":"Jenna McBayne","email":"jmcbaynehh@issuu.com"},
{"id":631,"name":"Ali Ferrao","email":"aferraohi@nationalgeographic.com"},
{"id":632,"name":"Johna Liepins","email":"jliepinshj@digg.com"},
{"id":633,"name":"Michale Dolden","email":"mdoldenhk@newsvine.com"},
{"id":634,"name":"Bartholomew Skip","email":"bskiphl@msu.edu"},
{"id":635,"name":"Maurie Jerrom","email":"mjerromhm@multiply.com"},
{"id":636,"name":"Laney Bedborough","email":"lbedboroughhn@hp.com"},
{"id":637,"name":"Richy De Blasiis","email":"rdeho@virginia.edu"},
{"id":638,"name":"Pippa McReidy","email":"pmcreidyhp@e-recht24.de"},
{"id":639,"name":"Leigh Schlagtmans","email":"lschlagtmanshq@goo.gl"},
{"id":640,"name":"Maximo Puvia","email":"mpuviahr@free.fr"},
{"id":641,"name":"Giselbert Tothacot","email":"gtothacoths@accuweather.com"},
{"id":642,"name":"Giselbert Sambrook","email":"gsambrookht@ted.com"},
{"id":643,"name":"Cece Issacson","email":"cissacsonhu@wiley.com"},
{"id":644,"name":"Korney Hele","email":"khelehv@accuweather.com"},
{"id":645,"name":"Ellynn Bodsworth","email":"ebodsworthhw@microsoft.com"},
{"id":646,"name":"Cindie Woodfin","email":"cwoodfinhx@opera.com"},
{"id":647,"name":"Barclay Coal","email":"bcoalhy@mayoclinic.com"},
{"id":648,"name":"Regan Charrette","email":"rcharrettehz@apple.com"},
{"id":649,"name":"Morgun Elbourne","email":"melbournei0@irs.gov"},
{"id":650,"name":"Tammie Lorey","email":"tloreyi1@va.gov"},
{"id":651,"name":"Emlynne Boor","email":"eboori2@constantcontact.com"},
{"id":652,"name":"Lulu Bowser","email":"lbowseri3@state.gov"},
{"id":653,"name":"Warden Gillion","email":"wgillioni4@msu.edu"},
{"id":654,"name":"Waiter Warstall","email":"wwarstalli5@etsy.com"},
{"id":655,"name":"Lolly Dawidman","email":"ldawidmani6@dagondesign.com"},
{"id":656,"name":"Berkly MacMychem","email":"bmacmychemi7@mtv.com"},
{"id":657,"name":"Cyrillus Sivyer","email":"csivyeri8@odnoklassniki.ru"},
{"id":658,"name":"Norbert Divill","email":"ndivilli9@opensource.org"},
{"id":659,"name":"Charo Ramsbottom","email":"cramsbottomia@bing.com"},
{"id":660,"name":"Constance Ratledge","email":"cratledgeib@usgs.gov"},
{"id":661,"name":"Caty Cornewall","email":"ccornewallic@weibo.com"},
{"id":662,"name":"Ilsa Scotford","email":"iscotfordid@whitehouse.gov"},
{"id":663,"name":"Janenna Elsie","email":"jelsieie@goo.gl"},
{"id":664,"name":"Lucien Garrood","email":"lgarroodif@alexa.com"},
{"id":665,"name":"Nettle Dunford","email":"ndunfordig@wikia.com"},
{"id":666,"name":"Brigid Sambells","email":"bsambellsih@yellowpages.com"},
{"id":667,"name":"Koren Radage","email":"kradageii@geocities.jp"},
{"id":668,"name":"Alisa Absalom","email":"aabsalomij@prweb.com"},
{"id":669,"name":"Averil Antonsson","email":"aantonssonik@mayoclinic.com"},
{"id":670,"name":"Hilarius MacNess","email":"hmacnessil@tripod.com"},
{"id":671,"name":"Bibby Cooksey","email":"bcookseyim@state.gov"},
{"id":672,"name":"Quillan Finlayson","email":"qfinlaysonin@omniture.com"},
{"id":673,"name":"Alexandros Eby","email":"aebyio@alexa.com"},
{"id":674,"name":"Charity Yglesia","email":"cyglesiaip@alibaba.com"},
{"id":675,"name":"Gennie Kalker","email":"gkalkeriq@go.com"},
{"id":676,"name":"Vin Esparza","email":"vesparzair@globo.com"},
{"id":677,"name":"Cassaundra Rainy","email":"crainyis@ed.gov"},
{"id":678,"name":"Elene Bemand","email":"ebemandit@biblegateway.com"},
{"id":679,"name":"Kora Langworthy","email":"klangworthyiu@spotify.com"},
{"id":680,"name":"Niccolo Adrien","email":"nadrieniv@tuttocitta.it"},
{"id":681,"name":"Elmo Pietron","email":"epietroniw@reuters.com"},
{"id":682,"name":"Jarret Crucitti","email":"jcrucittiix@discuz.net"},
{"id":683,"name":"Cassandry McGloin","email":"cmcgloiniy@yahoo.com"},
{"id":684,"name":"Arielle McDuffy","email":"amcduffyiz@reverbnation.com"},
{"id":685,"name":"Zelma Peat","email":"zpeatj0@samsung.com"},
{"id":686,"name":"Hayyim Chawner","email":"hchawnerj1@army.mil"},
{"id":687,"name":"Izabel Brach","email":"ibrachj2@si.edu"},
{"id":688,"name":"Curry Jedryka","email":"cjedrykaj3@weather.com"},
{"id":689,"name":"Frasquito Edlington","email":"fedlingtonj4@nsw.gov.au"},
{"id":690,"name":"Alys Ram","email":"aramj5@instagram.com"},
{"id":691,"name":"Arielle Walder","email":"awalderj6@unicef.org"},
{"id":692,"name":"Ricard Macconaghy","email":"rmacconaghyj7@wordpress.com"},
{"id":693,"name":"Barty Pinkard","email":"bpinkardj8@smh.com.au"},
{"id":694,"name":"Darcey Comben","email":"dcombenj9@webs.com"},
{"id":695,"name":"Sharl Le Noire","email":"sleja@skyrock.com"},
{"id":696,"name":"Son Haulkham","email":"shaulkhamjb@360.cn"},
{"id":697,"name":"Allyn Cowp","email":"acowpjc@soundcloud.com"},
{"id":698,"name":"Ransell Coarser","email":"rcoarserjd@si.edu"},
{"id":699,"name":"Gayler Landal","email":"glandalje@dropbox.com"},
{"id":700,"name":"Norri Piatto","email":"npiattojf@berkeley.edu"},
{"id":701,"name":"Neale Faulo","email":"nfaulojg@facebook.com"},
{"id":702,"name":"Jacquie Tumielli","email":"jtumiellijh@economist.com"},
{"id":703,"name":"Tabbitha Dear","email":"tdearji@vistaprint.com"},
{"id":704,"name":"Donal Skelly","email":"dskellyjj@jigsy.com"},
{"id":705,"name":"Kiah Sporrij","email":"ksporrijjk@nba.com"},
{"id":706,"name":"Cicily Torvey","email":"ctorveyjl@i2i.jp"},
{"id":707,"name":"Lorrie Gilchrest","email":"lgilchrestjm@pcworld.com"},
{"id":708,"name":"Gael Carnell","email":"gcarnelljn@issuu.com"},
{"id":709,"name":"Brnaby Diano","email":"bdianojo@wiley.com"},
{"id":710,"name":"Erwin Stower","email":"estowerjp@printfriendly.com"},
{"id":711,"name":"Ford Gerling","email":"fgerlingjq@wix.com"},
{"id":712,"name":"Gav McCullough","email":"gmcculloughjr@friendfeed.com"},
{"id":713,"name":"Alissa Childers","email":"achildersjs@flickr.com"},
{"id":714,"name":"Marthena Guinan","email":"mguinanjt@skyrock.com"},
{"id":715,"name":"Ailsun Laurentin","email":"alaurentinju@seesaa.net"},
{"id":716,"name":"Terrie Weaver","email":"tweaverjv@mit.edu"},
{"id":717,"name":"Julee Dorn","email":"jdornjw@noaa.gov"},
{"id":718,"name":"Alexia Eardley","email":"aeardleyjx@dailymail.co.uk"},
{"id":719,"name":"Winifred Dingley","email":"wdingleyjy@bravesites.com"},
{"id":720,"name":"Jillana Ranking","email":"jrankingjz@artisteer.com"},
{"id":721,"name":"Bryant Husby","email":"bhusbyk0@tiny.cc"},
{"id":722,"name":"Pat Golde","email":"pgoldek1@xing.com"},
{"id":723,"name":"Prue Glason","email":"pglasonk2@sphinn.com"},
{"id":724,"name":"Neall Wailes","email":"nwailesk3@oaic.gov.au"},
{"id":725,"name":"Jeanelle Norrington","email":"jnorringtonk4@answers.com"},
{"id":726,"name":"Wolfy Brislawn","email":"wbrislawnk5@skyrock.com"},
{"id":727,"name":"Alexina Chicotti","email":"achicottik6@whitehouse.gov"},
{"id":728,"name":"Katti Ivett","email":"kivettk7@csmonitor.com"},
{"id":729,"name":"Mandel Norrey","email":"mnorreyk8@wufoo.com"},
{"id":730,"name":"Morgan Schiesterl","email":"mschiesterlk9@wikipedia.org"},
{"id":731,"name":"Britni Bantham","email":"bbanthamka@deviantart.com"},
{"id":732,"name":"Serge Wooler","email":"swoolerkb@instagram.com"},
{"id":733,"name":"Shae Morter","email":"smorterkc@smugmug.com"},
{"id":734,"name":"Mylo Hryniewicki","email":"mhryniewickikd@google.co.uk"},
{"id":735,"name":"Rollie MacCrann","email":"rmaccrannke@over-blog.com"},
{"id":736,"name":"Daren Lacoste","email":"dlacostekf@tuttocitta.it"},
{"id":737,"name":"Lotta Petrou","email":"lpetroukg@nature.com"},
{"id":738,"name":"Anthea Northing","email":"anorthingkh@theguardian.com"},
{"id":739,"name":"Rob Winnister","email":"rwinnisterki@yellowpages.com"},
{"id":740,"name":"Gregg McGeever","email":"gmcgeeverkj@skype.com"},
{"id":741,"name":"Boyd Grattan","email":"bgrattankk@ocn.ne.jp"},
{"id":742,"name":"Glyn Robelow","email":"grobelowkl@ucoz.ru"},
{"id":743,"name":"Obadias Betz","email":"obetzkm@ihg.com"},
{"id":744,"name":"Kitty Buxton","email":"kbuxtonkn@amazon.co.uk"},
{"id":745,"name":"Annis Graver","email":"agraverko@weebly.com"},
{"id":746,"name":"Eolanda Schulter","email":"eschulterkp@deliciousdays.com"},
{"id":747,"name":"Charlot Shurmer","email":"cshurmerkq@bloomberg.com"},
{"id":748,"name":"Alisa Riccione","email":"ariccionekr@redcross.org"},
{"id":749,"name":"Selie Kaminski","email":"skaminskiks@illinois.edu"},
{"id":750,"name":"Kristofor Jochens","email":"kjochenskt@whitehouse.gov"},
{"id":751,"name":"Fawne Liles","email":"flilesku@techcrunch.com"},
{"id":752,"name":"Beatriz MacAne","email":"bmacanekv@squarespace.com"},
{"id":753,"name":"Barbaraanne Slemming","email":"bslemmingkw@diigo.com"},
{"id":754,"name":"Gerri Sabati","email":"gsabatikx@columbia.edu"},
{"id":755,"name":"Jacquie Takkos","email":"jtakkosky@multiply.com"},
{"id":756,"name":"Rozina Wrotchford","email":"rwrotchfordkz@jigsy.com"},
{"id":757,"name":"Merrill Brennen","email":"mbrennenl0@miitbeian.gov.cn"},
{"id":758,"name":"Durward Loiterton","email":"dloitertonl1@hostgator.com"},
{"id":759,"name":"Ulick Tidbold","email":"utidboldl2@hugedomains.com"},
{"id":760,"name":"Minetta Remington","email":"mremingtonl3@google.co.jp"},
{"id":761,"name":"Rudiger Feeny","email":"rfeenyl4@parallels.com"},
{"id":762,"name":"Baxy Edbrooke","email":"bedbrookel5@prlog.org"},
{"id":763,"name":"Stillmann Palfreeman","email":"spalfreemanl6@wix.com"},
{"id":764,"name":"Alfy Coppens","email":"acoppensl7@reference.com"},
{"id":765,"name":"Dianemarie Pestor","email":"dpestorl8@bloglovin.com"},
{"id":766,"name":"Jena Sebyer","email":"jsebyerl9@fastcompany.com"},
{"id":767,"name":"Sofie Mohammad","email":"smohammadla@huffingtonpost.com"},
{"id":768,"name":"Karolina Paolucci","email":"kpaoluccilb@paypal.com"},
{"id":769,"name":"Vivia Clements","email":"vclementslc@tmall.com"},
{"id":770,"name":"Matilda Balser","email":"mbalserld@hud.gov"},
{"id":771,"name":"Waiter Chisholm","email":"wchisholmle@hp.com"},
{"id":772,"name":"Annmaria Gartsyde","email":"agartsydelf@youku.com"},
{"id":773,"name":"Tad Fernao","email":"tfernaolg@opensource.org"},
{"id":774,"name":"Vevay Caffrey","email":"vcaffreylh@mashable.com"},
{"id":775,"name":"Ottilie Pring","email":"opringli@howstuffworks.com"},
{"id":776,"name":"Carine Fulton","email":"cfultonlj@fastcompany.com"},
{"id":777,"name":"Wilfred Blaylock","email":"wblaylocklk@sourceforge.net"},
{"id":778,"name":"Hewett Barthod","email":"hbarthodll@rediff.com"},
{"id":779,"name":"Cesaro Gumn","email":"cgumnlm@deviantart.com"},
{"id":780,"name":"Raffaello Childrens","email":"rchildrensln@bizjournals.com"},
{"id":781,"name":"Jazmin Spuner","email":"jspunerlo@google.com"},
{"id":782,"name":"Adolphus Kelshaw","email":"akelshawlp@zdnet.com"},
{"id":783,"name":"Reinwald Silverthorn","email":"rsilverthornlq@chron.com"},
{"id":784,"name":"Moses Fischer","email":"mfischerlr@dot.gov"},
{"id":785,"name":"Brandtr Le Gassick","email":"blels@simplemachines.org"},
{"id":786,"name":"Abagail Falls","email":"afallslt@cpanel.net"},
{"id":787,"name":"Vicki MacIlory","email":"vmacilorylu@mediafire.com"},
{"id":788,"name":"Miguela Toderi","email":"mtoderilv@telegraph.co.uk"},
{"id":789,"name":"Federica Duffyn","email":"fduffynlw@over-blog.com"},
{"id":790,"name":"Billy Johnston","email":"bjohnstonlx@wisc.edu"},
{"id":791,"name":"Nadiya Cheal","email":"ncheally@shinystat.com"},
{"id":792,"name":"Prisca Jenken","email":"pjenkenlz@myspace.com"},
{"id":793,"name":"Jaimie Norkett","email":"jnorkettm0@cnn.com"},
{"id":794,"name":"Henry Narracott","email":"hnarracottm1@cafepress.com"},
{"id":795,"name":"Emelina Darinton","email":"edarintonm2@yandex.ru"},
{"id":796,"name":"Abby Penton","email":"apentonm3@ebay.com"},
{"id":797,"name":"Lothaire Demanche","email":"ldemanchem4@dion.ne.jp"},
{"id":798,"name":"Elwira Treweek","email":"etreweekm5@washingtonpost.com"},
{"id":799,"name":"Armando Filipczynski","email":"afilipczynskim6@youku.com"},
{"id":800,"name":"Doria Dietsche","email":"ddietschem7@reuters.com"},
{"id":801,"name":"Charita Nucator","email":"cnucatorm8@live.com"},
{"id":802,"name":"Kerrin Jorczyk","email":"kjorczykm9@quantcast.com"},
{"id":803,"name":"Fedora Mateescu","email":"fmateescuma@boston.com"},
{"id":804,"name":"Merl Pesik","email":"mpesikmb@alibaba.com"},
{"id":805,"name":"Hervey Swabey","email":"hswabeymc@devhub.com"},
{"id":806,"name":"Suzette Blindmann","email":"sblindmannmd@sciencedirect.com"},
{"id":807,"name":"Skip Hassewell","email":"shassewellme@cbslocal.com"},
{"id":808,"name":"Missie Quelch","email":"mquelchmf@gizmodo.com"},
{"id":809,"name":"Percy Steckings","email":"psteckingsmg@forbes.com"},
{"id":810,"name":"Raviv Stiles","email":"rstilesmh@illinois.edu"},
{"id":811,"name":"Natalya Fick","email":"nfickmi@meetup.com"},
{"id":812,"name":"Kenna Sidworth","email":"ksidworthmj@skype.com"},
{"id":813,"name":"Natalya Hawick","email":"nhawickmk@1688.com"},
{"id":814,"name":"Darelle Bensley","email":"dbensleyml@sbwire.com"},
{"id":815,"name":"Irene Brownbill","email":"ibrownbillmm@posterous.com"},
{"id":816,"name":"Keelby Gillebert","email":"kgillebertmn@a8.net"},
{"id":817,"name":"Jermayne Vagg","email":"jvaggmo@yellowpages.com"},
{"id":818,"name":"Dermot Rooze","email":"droozemp@abc.net.au"},
{"id":819,"name":"Ronny Gebb","email":"rgebbmq@wired.com"},
{"id":820,"name":"Morgan Sallnow","email":"msallnowmr@ebay.co.uk"},
{"id":821,"name":"Phillipp Bleeze","email":"pbleezems@phpbb.com"},
{"id":822,"name":"Ezri Matteoli","email":"ematteolimt@scientificamerican.com"},
{"id":823,"name":"Gisella Speeding","email":"gspeedingmu@addthis.com"},
{"id":824,"name":"Foster Bahlmann","email":"fbahlmannmv@weather.com"},
{"id":825,"name":"Mahmoud Reef","email":"mreefmw@blinklist.com"},
{"id":826,"name":"Aland Drinkhill","email":"adrinkhillmx@eventbrite.com"},
{"id":827,"name":"Mavis Swidenbank","email":"mswidenbankmy@cyberchimps.com"},
{"id":828,"name":"Rudyard Fury","email":"rfurymz@un.org"},
{"id":829,"name":"Redford Briton","email":"rbritonn0@constantcontact.com"},
{"id":830,"name":"Egon Pettecrew","email":"epettecrewn1@zimbio.com"},
{"id":831,"name":"Monroe Dowdle","email":"mdowdlen2@liveinternet.ru"},
{"id":832,"name":"Shepherd Gaylor","email":"sgaylorn3@sbwire.com"},
{"id":833,"name":"Lemar Zouch","email":"lzouchn4@toplist.cz"},
{"id":834,"name":"Zechariah Hancox","email":"zhancoxn5@intel.com"},
{"id":835,"name":"Colas Lawly","email":"clawlyn6@google.es"},
{"id":836,"name":"Skipper Wenn","email":"swennn7@last.fm"},
{"id":837,"name":"Gretal Marin","email":"gmarinn8@cloudflare.com"},
{"id":838,"name":"Cosmo Dumini","email":"cduminin9@furl.net"},
{"id":839,"name":"Shantee Langabeer","email":"slangabeerna@wisc.edu"},
{"id":840,"name":"Talbert Giraudy","email":"tgiraudynb@chicagotribune.com"},
{"id":841,"name":"Granny Solan","email":"gsolannc@thetimes.co.uk"},
{"id":842,"name":"Briney Foux","email":"bfouxnd@wp.com"},
{"id":843,"name":"Mile Blaver","email":"mblaverne@lulu.com"},
{"id":844,"name":"Marijo Saltmarsh","email":"msaltmarshnf@ihg.com"},
{"id":845,"name":"Gina Ouslem","email":"gouslemng@wiley.com"},
{"id":846,"name":"Willard Brundale","email":"wbrundalenh@sciencedaily.com"},
{"id":847,"name":"Kyla Cowterd","email":"kcowterdni@yelp.com"},
{"id":848,"name":"Lettie Grayland","email":"lgraylandnj@un.org"},
{"id":849,"name":"Dalenna Tyson","email":"dtysonnk@simplemachines.org"},
{"id":850,"name":"Reynold Iacovino","email":"riacovinonl@free.fr"},
{"id":851,"name":"Elyse Dodgshon","email":"edodgshonnm@indiegogo.com"},
{"id":852,"name":"Alverta Toye","email":"atoyenn@washingtonpost.com"},
{"id":853,"name":"Lek Dart","email":"ldartno@samsung.com"},
{"id":854,"name":"Gothart Hamper","email":"ghampernp@nature.com"},
{"id":855,"name":"Emmalyn Oxburgh","email":"eoxburghnq@t-online.de"},
{"id":856,"name":"Vernice de Aguirre","email":"vdenr@pcworld.com"},
{"id":857,"name":"Enid Cordel","email":"ecordelns@stanford.edu"},
{"id":858,"name":"Ulick Adolf","email":"uadolfnt@scribd.com"},
{"id":859,"name":"Rhiamon Porter","email":"rporternu@squarespace.com"},
{"id":860,"name":"Townie Sutcliff","email":"tsutcliffnv@amazon.de"},
{"id":861,"name":"Ruprecht O' Molan","email":"ronw@cbsnews.com"},
{"id":862,"name":"Izaak Robbs","email":"irobbsnx@cbsnews.com"},
{"id":863,"name":"Todd Kreutzer","email":"tkreutzerny@mayoclinic.com"},
{"id":864,"name":"Bettye Vina","email":"bvinanz@ocn.ne.jp"},
{"id":865,"name":"Javier Clingan","email":"jclingano0@123-reg.co.uk"},
{"id":866,"name":"Ruddie Doring","email":"rdoringo1@cyberchimps.com"},
{"id":867,"name":"Deeyn Jeffs","email":"djeffso2@usa.gov"},
{"id":868,"name":"Cesar Girardey","email":"cgirardeyo3@constantcontact.com"},
{"id":869,"name":"Julietta Abad","email":"jabado4@weebly.com"},
{"id":870,"name":"Madonna Charrett","email":"mcharretto5@topsy.com"},
{"id":871,"name":"Auria Guilliatt","email":"aguilliatto6@arstechnica.com"},
{"id":872,"name":"Agretha Pailin","email":"apailino7@state.gov"},
{"id":873,"name":"Felicity Roncelli","email":"froncellio8@usa.gov"},
{"id":874,"name":"Anya Eskrick","email":"aeskricko9@wunderground.com"},
{"id":875,"name":"Elbert Standage","email":"estandageoa@phoca.cz"},
{"id":876,"name":"Ginnie Seyers","email":"gseyersob@auda.org.au"},
{"id":877,"name":"Elberta Rounsivall","email":"erounsivalloc@blogs.com"},
{"id":878,"name":"Johnny Shemelt","email":"jshemeltod@cisco.com"},
{"id":879,"name":"Brina Maggiore","email":"bmaggioreoe@utexas.edu"},
{"id":880,"name":"Tanitansy Shelper","email":"tshelperof@geocities.jp"},
{"id":881,"name":"Zebulon Aarons","email":"zaaronsog@umn.edu"},
{"id":882,"name":"Aurelia Fairbridge","email":"afairbridgeoh@dion.ne.jp"},
{"id":883,"name":"Faulkner Hamfleet","email":"fhamfleetoi@state.tx.us"},
{"id":884,"name":"Bonita MacKellen","email":"bmackellenoj@home.pl"},
{"id":885,"name":"Beatriz Brinicombe","email":"bbrinicombeok@qq.com"},
{"id":886,"name":"Cherin Dowdell","email":"cdowdellol@netlog.com"},
{"id":887,"name":"Blancha Tapply","email":"btapplyom@google.co.jp"},
{"id":888,"name":"Verna Brahan","email":"vbrahanon@taobao.com"},
{"id":889,"name":"Ludovico McNeil","email":"lmcneiloo@addthis.com"},
{"id":890,"name":"Vickie Pharrow","email":"vpharrowop@google.com"},
{"id":891,"name":"Stacy Dranfield","email":"sdranfieldoq@eepurl.com"},
{"id":892,"name":"Clive Bradnum","email":"cbradnumor@delicious.com"},
{"id":893,"name":"Reagan Roscamps","email":"rroscampsos@msu.edu"},
{"id":894,"name":"Celia Nise","email":"cniseot@nasa.gov"},
{"id":895,"name":"Liv Hamsher","email":"lhamsherou@house.gov"},
{"id":896,"name":"Sterne Fronsek","email":"sfronsekov@prlog.org"},
{"id":897,"name":"Ludvig Bedford","email":"lbedfordow@comsenz.com"},
{"id":898,"name":"Camille Fittes","email":"cfittesox@harvard.edu"},
{"id":899,"name":"Rockwell Seville","email":"rsevilleoy@edublogs.org"},
{"id":900,"name":"Rebekah Georgins","email":"rgeorginsoz@earthlink.net"},
{"id":901,"name":"Shawn Vida","email":"svidap0@surveymonkey.com"},
{"id":902,"name":"Charyl Arnao","email":"carnaop1@ehow.com"},
{"id":903,"name":"Adams Mocquer","email":"amocquerp2@is.gd"},
{"id":904,"name":"Rodie Quiney","email":"rquineyp3@cam.ac.uk"},
{"id":905,"name":"Elicia Wickersham","email":"ewickershamp4@senate.gov"},
{"id":906,"name":"Charmion Ashley","email":"cashleyp5@webs.com"},
{"id":907,"name":"Charlotta Clubley","email":"cclubleyp6@altervista.org"},
{"id":908,"name":"Jemimah Alvar","email":"jalvarp7@webmd.com"},
{"id":909,"name":"Rollie Python","email":"rpythonp8@home.pl"},
{"id":910,"name":"Adriana Becerro","email":"abecerrop9@prlog.org"},
{"id":911,"name":"Amandie MacPadene","email":"amacpadenepa@example.com"},
{"id":912,"name":"Chrissy Brockherst","email":"cbrockherstpb@desdev.cn"},
{"id":913,"name":"Dode McCawley","email":"dmccawleypc@comcast.net"},
{"id":914,"name":"Chuck St. Leger","email":"cstpd@vkontakte.ru"},
{"id":915,"name":"Richmond Mutch","email":"rmutchpe@weibo.com"},
{"id":916,"name":"Emmi Mattock","email":"emattockpf@cdc.gov"},
{"id":917,"name":"Dirk Congrave","email":"dcongravepg@theguardian.com"},
{"id":918,"name":"Raina Moppett","email":"rmoppettph@adobe.com"},
{"id":919,"name":"Beltran Workman","email":"bworkmanpi@washington.edu"},
{"id":920,"name":"Gordan Birchner","email":"gbirchnerpj@topsy.com"},
{"id":921,"name":"Anne-corinne Domenicone","email":"adomeniconepk@europa.eu"},
{"id":922,"name":"Hew Yurevich","email":"hyurevichpl@slashdot.org"},
{"id":923,"name":"Rickie Chicchetto","email":"rchicchettopm@chronoengine.com"},
{"id":924,"name":"Rozella Gotecliffe","email":"rgotecliffepn@xinhuanet.com"},
{"id":925,"name":"Griff Cases","email":"gcasespo@oakley.com"},
{"id":926,"name":"Caralie Yitzovicz","email":"cyitzoviczpp@dot.gov"},
{"id":927,"name":"Oralle Edlyne","email":"oedlynepq@google.co.uk"},
{"id":928,"name":"Arlyne Caulcutt","email":"acaulcuttpr@globo.com"},
{"id":929,"name":"Britt Habden","email":"bhabdenps@yahoo.co.jp"},
{"id":930,"name":"Paulo MacDermand","email":"pmacdermandpt@over-blog.com"},
{"id":931,"name":"Sheila-kathryn Christescu","email":"schristescupu@desdev.cn"},
{"id":932,"name":"Gawain Rizzardini","email":"grizzardinipv@cnbc.com"},
{"id":933,"name":"Lammond Fontin","email":"lfontinpw@prlog.org"},
{"id":934,"name":"Antoni Cranney","email":"acranneypx@a8.net"},
{"id":935,"name":"Jarid Gurry","email":"jgurrypy@facebook.com"},
{"id":936,"name":"Der Dadson","email":"ddadsonpz@soundcloud.com"},
{"id":937,"name":"Sharleen Bigmore","email":"sbigmoreq0@alexa.com"},
{"id":938,"name":"Janaye Sperwell","email":"jsperwellq1@taobao.com"},
{"id":939,"name":"Galen Anstee","email":"gansteeq2@behance.net"},
{"id":940,"name":"Ray Workman","email":"rworkmanq3@github.io"},
{"id":941,"name":"Amery Muckart","email":"amuckartq4@nature.com"},
{"id":942,"name":"Erminia Fontel","email":"efontelq5@bbc.co.uk"},
{"id":943,"name":"Corenda Yeldham","email":"cyeldhamq6@sfgate.com"},
{"id":944,"name":"Jaclyn Grimditch","email":"jgrimditchq7@tamu.edu"},
{"id":945,"name":"Cleo Lannon","email":"clannonq8@jalbum.net"},
{"id":946,"name":"Miller Pessolt","email":"mpessoltq9@mayoclinic.com"},
{"id":947,"name":"Kayne Coldtart","email":"kcoldtartqa@cafepress.com"},
{"id":948,"name":"Gard Mars","email":"gmarsqb@deliciousdays.com"},
{"id":949,"name":"Kaiser Brundell","email":"kbrundellqc@apache.org"},
{"id":950,"name":"Beau Braiden","email":"bbraidenqd@cpanel.net"},
{"id":951,"name":"Sheffy Harber","email":"sharberqe@mtv.com"},
{"id":952,"name":"Elbert McSporrin","email":"emcsporrinqf@pen.io"},
{"id":953,"name":"Reidar Rosengart","email":"rrosengartqg@hubpages.com"},
{"id":954,"name":"Ardyth Hardson","email":"ahardsonqh@virginia.edu"},
{"id":955,"name":"Mathias Fawcus","email":"mfawcusqi@thetimes.co.uk"},
{"id":956,"name":"Lilli Foulkes","email":"lfoulkesqj@wiley.com"},
{"id":957,"name":"Scott Pantridge","email":"spantridgeqk@sakura.ne.jp"},
{"id":958,"name":"Hermie Bleackley","email":"hbleackleyql@java.com"},
{"id":959,"name":"Hollyanne Pemberton","email":"hpembertonqm@privacy.gov.au"},
{"id":960,"name":"Shanon Garrettson","email":"sgarrettsonqn@mozilla.com"},
{"id":961,"name":"Lyndsie Issit","email":"lissitqo@php.net"},
{"id":962,"name":"Patricio Cadwaladr","email":"pcadwaladrqp@mozilla.com"},
{"id":963,"name":"Emeline Bartrop","email":"ebartropqq@pagesperso-orange.fr"},
{"id":964,"name":"Jamaal Malarkey","email":"jmalarkeyqr@geocities.com"},
{"id":965,"name":"Amalie Allebone","email":"aalleboneqs@businesswire.com"},
{"id":966,"name":"Ania MacIllrick","email":"amacillrickqt@businessinsider.com"},
{"id":967,"name":"Sampson Ollive","email":"sollivequ@bravesites.com"},
{"id":968,"name":"Jay Toland","email":"jtolandqv@nhs.uk"},
{"id":969,"name":"Bink Goodbody","email":"bgoodbodyqw@4shared.com"},
{"id":970,"name":"Jud Cristofalo","email":"jcristofaloqx@jimdo.com"},
{"id":971,"name":"Jacqueline Lygo","email":"jlygoqy@latimes.com"},
{"id":972,"name":"Ferd Usherwood","email":"fusherwoodqz@npr.org"},
{"id":973,"name":"Iago Collingdon","email":"icollingdonr0@tripod.com"},
{"id":974,"name":"Hamil Badland","email":"hbadlandr1@twitter.com"},
{"id":975,"name":"Riki Hatchell","email":"rhatchellr2@bloglovin.com"},
{"id":976,"name":"Jayson Lory","email":"jloryr3@cnet.com"},
{"id":977,"name":"Elwood Breydin","email":"ebreydinr4@mac.com"},
{"id":978,"name":"Cathrine Holton","email":"choltonr5@guardian.co.uk"},
{"id":979,"name":"Hermann Casper","email":"hcasperr6@booking.com"},
{"id":980,"name":"Cesare MacAne","email":"cmacaner7@army.mil"},
{"id":981,"name":"Arabel Giaomozzo","email":"agiaomozzor8@usatoday.com"},
{"id":982,"name":"Lilah Le Marquis","email":"ller9@tinyurl.com"},
{"id":983,"name":"Fitzgerald Davydzenko","email":"fdavydzenkora@vkontakte.ru"},
{"id":984,"name":"Bunny Whittleton","email":"bwhittletonrb@technorati.com"},
{"id":985,"name":"Idalina Trusse","email":"itrusserc@dagondesign.com"},
{"id":986,"name":"Celia Morican","email":"cmoricanrd@state.tx.us"},
{"id":987,"name":"Burlie Bezants","email":"bbezantsre@ow.ly"},
{"id":988,"name":"Evvy Seeking","email":"eseekingrf@newsvine.com"},
{"id":989,"name":"Malina Duffett","email":"mduffettrg@google.com.au"},
{"id":990,"name":"Ken Anetts","email":"kanettsrh@abc.net.au"},
{"id":991,"name":"Eberhard Burberow","email":"eburberowri@gmpg.org"},
{"id":992,"name":"Tracy Matzaitis","email":"tmatzaitisrj@chron.com"},
{"id":993,"name":"Cory De Witt","email":"cderk@wikimedia.org"},
{"id":994,"name":"Renae Shelford","email":"rshelfordrl@netscape.com"},
{"id":995,"name":"Clerc Le Barre","email":"clerm@uiuc.edu"},
{"id":996,"name":"Kerr Francesch","email":"kfranceschrn@tiny.cc"},
{"id":997,"name":"Giovanna Haysey","email":"ghayseyro@webeden.co.uk"},
{"id":998,"name":"Abbott Pyrke","email":"apyrkerp@dmoz.org"},
{"id":999,"name":"Petey Souttar","email":"psouttarrq@nifty.com"},
{"id":1000,"name":"Nowell Dumbrill","email":"ndumbrillrr@blogtalkradio.com"}]